calculate_future_date/__init__.py
calculate_future_date/mycalc.py
calculate_future_date-0.1.0.dist-info/entry_points.txt
calculate_future_date-0.1.0.dist-info/WHEEL
calculate_future_date-0.1.0.dist-info/METADATA
calculate_future_date-0.1.0.dist-info/RECORD
